ai_helpers/__init__.py
ai_helpers/_version.py
ai_helpers/core.py
ai_helpers_yourname-0.0.1.dist-info/METADATA
ai_helpers_yourname-0.0.1.dist-info/WHEEL
ai_helpers_yourname-0.0.1.dist-info/top_level.txt
ai_helpers_yourname-0.0.1.dist-info/RECORD
